tracereq_sdk/__init__.py
tracereq_sdk/api.py
tracereq_sdk/client.py
tracereq_sdk/constants.py
tracereq_sdk/customlib.py
tracereq_sdk/engine.py
tracereq_sdk/tracing.py
tracereq_sdk/transport.py
tracereq_sdk/integrations/__init__.py
tracereq_sdk/integrations/flasklib.py
tracereq_sdk-1.0.2.dist-info/LICENSE
tracereq_sdk-1.0.2.dist-info/METADATA
tracereq_sdk-1.0.2.dist-info/WHEEL
tracereq_sdk-1.0.2.dist-info/top_level.txt
tracereq_sdk-1.0.2.dist-info/RECORD
