Metadata-Version: 2.1
Name: tracereq-sdk
Version: 1.0.2
Summary: Python client for TraceReq (https://tracereq.com)
Author-email: Prateek Sachan <ps@prateeksachan.com>
License: MIT License
Project-URL: Homepage, https://github.com/tracereq/python-tracereq-sdk
Keywords: flask,trace,api
Classifier: License :: OSI Approved :: MIT License
Classifier: Programming Language :: Python
Classifier: Programming Language :: Python :: 3
Requires-Python: >=3.6
License-File: LICENSE
Requires-Dist: urllib3 (>=1.26.16) ; python_version >= "3.6"
Provides-Extra: dev
Requires-Dist: pip-tools ; extra == 'dev'
